{
  "tracked_deals": [
    {
      "route_label": "Tashkent -> Istanbul",
      "latest_price": 160,
      "average_price": 162.57,
      "pct_below_average": 1.6,
      "is_deal": true,
      "detection_method": "isolation_forest",
      "data_points_so_far": 7
    },
    {
      "route_label": "Tashkent -> Seoul",
      "latest_price": 214,
      "average_price": 214.43,
      "pct_below_average": 0.2,
      "is_deal": true,
      "detection_method": "isolation_forest",
      "data_points_so_far": 7
    },
    {
      "route_label": "Samarkand -> Moscow",
      "latest_price": 76,
      "average_price": 76.0,
      "pct_below_average": 0.0,
      "is_deal": false,
      "detection_method": "isolation_forest",
      "data_points_so_far": 7
    },
    {
      "route_label": "Tashkent -> Venice",
      "latest_price": 200,
      "average_price": 200.0,
      "pct_below_average": 0.0,
      "is_deal": false,
      "detection_method": "isolation_forest",
      "data_points_so_far": 7
    },
    {
      "route_label": "Tashkent -> London",
      "latest_price": 224,
      "average_price": 216.14,
      "pct_below_average": -3.6,
      "is_deal": false,
      "detection_method": "isolation_forest",
      "data_points_so_far": 7
    },
    {
      "route_label": "Tashkent -> Barcelona",
      "latest_price": 238,
      "average_price": 229.57,
      "pct_below_average": -3.7,
      "is_deal": false,
      "detection_method": "isolation_forest",
      "data_points_so_far": 7
    },
    {
      "route_label": "Tashkent -> Bangkok",
      "latest_price": 213,
      "average_price": 204.14,
      "pct_below_average": -4.3,
      "is_deal": false,
      "detection_method": "isolation_forest",
      "data_points_so_far": 7
    },
    {
      "route_label": "Tashkent -> Dubai",
      "latest_price": 153,
      "average_price": 140.17,
      "pct_below_average": -9.2,
      "is_deal": false,
      "detection_method": "isolation_forest",
      "data_points_so_far": 6
    }
  ],
  "special_offers": [
    {
      "route_label": "Samarkand -> Fergana",
      "price": 62,
      "title": "Flight deals from Samarkand to Fergana",
      "airline": "Uzbekistan Airways"
    },
    {
      "route_label": "Samarkand -> Andijan",
      "price": 72,
      "title": "Flight deals from Samarkand to Andijan",
      "airline": "Uzbekistan Airways"
    },
    {
      "route_label": "Samarkand -> Baku",
      "price": 219,
      "title": "Flight deals from Samarkand to Baku",
      "airline": "Azerbaijan Airlines"
    },
    {
      "route_label": "Samarkand -> Batumi",
      "price": 276,
      "title": "Flight deals from Samarkand to Batumi",
      "airline": "Centrum Air"
    },
    {
      "route_label": "Samarkand -> Dubai",
      "price": 335,
      "title": "Flight deals from Samarkand to Dubai",
      "airline": "Flydubai"
    },
    {
      "route_label": "Samarkand -> Namangan",
      "price": 49,
      "title": "Flight deals from Samarkand to Namangan",
      "airline": "Uzbekistan Airways"
    },
    {
      "route_label": "Samarkand -> Astana",
      "price": 134,
      "title": "Flight deals from Samarkand to Astana",
      "airline": "Vietjet Qazaqstan"
    },
    {
      "route_label": "Samarkand -> Almaty",
      "price": 134,
      "title": "Flight deals from Samarkand to Almaty",
      "airline": "FlyArystan"
    },
    {
      "route_label": "Samarkand -> Chisinau",
      "price": 325,
      "title": "Flight deals from Samarkand to Chisinau",
      "airline": "Fly One"
    },
    {
      "route_label": "Tashkent -> Lahore",
      "price": 156,
      "title": "Flight deals from Tashkent to Lahore",
      "airline": "Centrum Air"
    },
    {
      "route_label": "Tashkent -> Samarkand",
      "price": 33,
      "title": "Flight deals from Tashkent to Samarkand",
      "airline": "Centrum Air"
    },
    {
      "route_label": "Tashkent -> Abu Dhabi",
      "price": 158,
      "title": "Flight deals from Tashkent to Abu Dhabi",
      "airline": "Air Arabia Abu Dhabi"
    },
    {
      "route_label": "Tashkent -> Chisinau",
      "price": 191,
      "title": "Flight deals from Tashkent to Chisinau",
      "airline": "Fly One"
    },
    {
      "route_label": "Tashkent -> Mumbai",
      "price": 157,
      "title": "Flight deals from Tashkent to Mumbai",
      "airline": "Uzbekistan Airways"
    },
    {
      "route_label": "Tashkent -> Delhi",
      "price": 138,
      "title": "Flight deals from Tashkent to Delhi",
      "airline": "Centrum Air"
    },
    {
      "route_label": "Tashkent -> Yerevan",
      "price": 141,
      "title": "Flight deals from Tashkent to Yerevan",
      "airline": "FLYONE Armenia"
    },
    {
      "route_label": "Tashkent -> Bukhara",
      "price": 56,
      "title": "Flight deals from Tashkent to Bukhara",
      "airline": "Uzbekistan Airways"
    },
    {
      "route_label": "Tashkent -> Izmir",
      "price": 151,
      "title": "Flight deals from Tashkent to Izmir",
      "airline": "SunExpress"
    }
  ]
}